discordauth/__init__.py
discordauth-0.1.0.dist-info/METADATA
discordauth-0.1.0.dist-info/WHEEL
discordauth-0.1.0.dist-info/RECORD
