Metadata-Version: 2.3
Name: discordauth
Version: 0.1.0
Summary: A simple Discord oauth2 library easy to use.
Author: Izak
Author-email: frdev.izak@gmail.com
Requires-Python: >=3.10
Classifier: Programming Language :: Python :: 3
Classifier: Programming Language :: Python :: 3.10
Classifier: Programming Language :: Python :: 3.11
Classifier: Programming Language :: Python :: 3.12
Classifier: Programming Language :: Python :: 3.13
Requires-Dist: httpx (>=0.28.1,<0.29.0)
